agentami/__init__.py
agentami/agents/__init__.py
agentami/agents/ami.py
agentami/tool_selector/__init__.py
agentami/tool_selector/tool_selector.py
agentami-1.0.1.dist-info/licenses/LICENSE
agentami-1.0.1.dist-info/METADATA
agentami-1.0.1.dist-info/WHEEL
agentami-1.0.1.dist-info/top_level.txt
agentami-1.0.1.dist-info/RECORD
